ElixirChengxusheji/README.md
ElixirChengxusheji/__init__.py
ElixirChengxusheji/__main__.py
ElixirChengxusheji/file.epub
ElixirChengxusheji/index.html
ElixirChengxusheji/css/__init__.py
ElixirChengxusheji/css/annotations.css
ElixirChengxusheji/css/main.css
ElixirChengxusheji/css/normalize.css
ElixirChengxusheji/css/popup.css
ElixirChengxusheji/font/__init__.py
ElixirChengxusheji/font/fontello.eot
ElixirChengxusheji/font/fontello.svg
ElixirChengxusheji/font/fontello.ttf
ElixirChengxusheji/font/fontello.woff
ElixirChengxusheji/img/__init__.py
ElixirChengxusheji/img/annotator-glyph-sprite.png
ElixirChengxusheji/img/annotator-icon-sprite.png
ElixirChengxusheji/img/apple-touch-icon.png
ElixirChengxusheji/img/cancelfullscreen.png
ElixirChengxusheji/img/close.png
ElixirChengxusheji/img/fullscreen.png
ElixirChengxusheji/img/loader.gif
ElixirChengxusheji/img/menu-icon.png
ElixirChengxusheji/img/save.png
ElixirChengxusheji/img/saved.png
ElixirChengxusheji/img/settings-s.png
ElixirChengxusheji/img/settings.png
ElixirChengxusheji/img/star.png
ElixirChengxusheji/js/__init__.py
ElixirChengxusheji/js/epub.js
ElixirChengxusheji/js/epub.min.js
ElixirChengxusheji/js/epub.min.map
ElixirChengxusheji/js/hooks.min.js
ElixirChengxusheji/js/hooks.min.map
ElixirChengxusheji/js/reader.js
ElixirChengxusheji/js/reader.js.map
ElixirChengxusheji/js/reader.min.js
ElixirChengxusheji/js/reader.min.map
ElixirChengxusheji/js/hooks/__init__.py
ElixirChengxusheji/js/hooks/extensions/__init__.py
ElixirChengxusheji/js/hooks/extensions/highlight.js
ElixirChengxusheji/js/libs/__init__.py
ElixirChengxusheji/js/libs/jquery.min.js
ElixirChengxusheji/js/libs/localforage.min.js
ElixirChengxusheji/js/libs/screenfull.js
ElixirChengxusheji/js/libs/screenfull.min.js
ElixirChengxusheji/js/libs/zip.min.js
ElixirChengxusheji/js/plugins/__init__.py
ElixirChengxusheji/js/plugins/hypothesis.js
ElixirChengxusheji/js/plugins/search.js
elixir_chengxusheji-2024.3.1.0.dist-info/METADATA
elixir_chengxusheji-2024.3.1.0.dist-info/WHEEL
elixir_chengxusheji-2024.3.1.0.dist-info/entry_points.txt
elixir_chengxusheji-2024.3.1.0.dist-info/top_level.txt
elixir_chengxusheji-2024.3.1.0.dist-info/RECORD
